[{
    "model": "store.user",
    "pk": 1,
    "fields": {
        "last_login": "2022-10-14T12:07:43.670Z",
        "is_superuser": true,
        "email": "",
        "is_staff": true,
        "is_active": true,
        "date_joined": "2022-09-28T08:53:18Z",
        "username": "kelvinchui6571@gmail.com",
        "password": "pbkdf2_sha256$320000$5JpNXrxfy5qWKNbpmflzHY$a8OBOyBOzbWsp36SdsPB4jpYw+61dkhKELWQd/0QpF8=",
        "first_name": "kelvin",
        "last_name": "chui",
        "phone": "0703719594",
        "birth_date": "1997-10-23",
        "profile_pic": "profile/kelvinchui6571@gmail.com/Screenshot_20220924-153454.png",
        "groups": [],
        "user_permissions": []
    }
}]